README.rst
contrapy.py
setup.cfg
setup.py
contrapy.egg-info/PKG-INFO
contrapy.egg-info/SOURCES.txt
contrapy.egg-info/dependency_links.txt
contrapy.egg-info/top_level.txt