Metadata-Version: 1.1
Name: contrapy
Version: 2018.1.30
Summary: Contracts for Python
Home-page: https://github.com/digitalmensch/contrapy
Author: Tobias Ammann
Author-email: UNKNOWN
License: MIT
Download-URL: https://pypi.python.org/pypi/contrapy
Keywords: contracts,contracts-programming
Platform: any
Classifier: Development Status :: 4 - Beta
Classifier: Intended Audience :: Developers
Classifier: License :: OSI Approved :: MIT License
Classifier: Operating System :: OS Independent
Classifier: Programming Language :: Python
Classifier: Programming Language :: Python :: 3.6
